{
  "resourceType": "ValueSet",
  "id": "BRNivelEducacional",
  "url": "http://rnds-fhir.saude.gov.br/ValueSet/BRNivelEducacional",
  "version": "0.1.0",
  "name": "BRNivelEducacional",
  "title": "Nível educacional",
  "status": "draft",
  "date": "2022-12-10T15:32:38-03:00",
  "publisher": "Comissão de Governança de Informação em Saúde (CGIS - UFG)",
  "contact": [
    {
      "name": "Comissão de Governança de Informação em Saúde (CGIS - UFG)",
      "telecom": [
        { "system": "url", "value": "https://cgis.ufg.br" },
        { "system": "email", "value": "kyriosdata@ufg.br" }
      ]
    }
  ],
  "description": "Identifica o nível educacional do paciente (maior obtido).\n\n**IMPORTANTE**: é preciso verificar a conformidade com a orientação formal\ndo Ministério da Educação.",
  "jurisdiction": [
    {
      "coding": [
        { "system": "urn:iso:std:iso:3166", "code": "BR", "display": "Brazil" }
      ]
    }
  ],
  "copyright": "This content LOINC® is copyright © 1995 Regenstrief Institute, Inc. and the LOINC Committee, and available at no cost under the license at http://loinc.org/terms-of-use",
  "compose": {
    "include": [
      {
        "system": "http://loinc.org",
        "concept": [
          { "code": "LA36-9", "display": "Ensino infantil ou menos" },
          { "code": "LA12456-2", "display": "Ensino fundamental" },
          { "code": "LA12457-0", "display": "Ensino médio" },
          { "code": "LA12458-8", "display": "Curso técnico" },
          { "code": "LA12460-4", "display": "Graduação" },
          { "code": "LA12461-2", "display": "Mestrado" },
          { "code": "LA12462-0", "display": "Doutorado" },
          { "code": "LA4489-6", "display": "Desconhecido" }
        ]
      }
    ]
  }
}
